{
  "item.purple.ready": "Clicca per quando sei Pronto!",
  "item.purple.not_ready": "Clicca per Cancellare",
  "item.purple.lobby": "Clicca per ritornare al Campo Base",
  "item.purple.spectate": "Clicca per entrare nella Modalità Spettatore",
  "item.purple.spectate_game": "Clicca per guardare la Partita",
  "item.purple.console_book": "Libro della Console",
  "item.purple.translate_book": "Libro Traduzioni",
  "item.purple.knockback_slimeball": "Yeet!",
  "item.purple.sharp_pufferfish": "Ouch!",
  "item.purple.edible_horse": "Quanto affamato?",
  "item.purple.space_helmet": "Casco Spaziale",
  "item.purple.super_fishing_rod": "Canna da Pesca di nightlibra",
  "item.purple.rock": "Sasso",
  "item.purple.small_mushroom": "Mini Fungo",
  "item.purple.chorus_fruit": "Frutto di Chorus Istantaneo",
  "item.purple.ender_pearl": "Perla di Ender",
  "item.purple.glow_horn": "Corno Luminoso",
  "item.purple.glow_horn.desc": "Rivela tutti i giocatori",
  "item.purple.totem_of_undying": "Totem dell'Immortalità",
  "item.purple.trident": "Tridente",
  "item.purple.safety_vest": "Gilè di Sicurezza",
  "item.purple.safety_vest.desc": "Blocca un colpo",
  "item.purple.prison_key": "Chiave della Prigione",
  "item.purple.prison_key.desc": "Colpisci qualcuno per imprigionarli",
  "item.purple.compass": "Bussola di Tracciamento",
  "item.purple.compass.desc": "Traccia il giocatore più vicino",
  "item.purple.freeze_time": "Ferma il Tempo",
  "item.purple.freeze_time.desc": "Tempo di congelamento per %ss",
  "item.purple.smoke_bomb": "Bomba Fumogena",
  "item.purple.antidote": "Antidoto",
  "item.purple.antidote.desc": "Curati",
  "item.purple.wind_charge": "Carica di Vento",
  "item.purple.revival_potion": "Elixer della Rinascita",
  "item.purple.revival_potion.desc.1": "Lancia su un giocatore morto",
  "item.purple.revival_potion.desc.2": "per rianimarli",
  "item.purple.artifact.lore": "Artefatto",
  "item.purple.artifact.frying_pan.name": "Padella",
  "item.purple.artifact.frying_pan.desc": "Perfetto per cucinare misteriose uova strapazzate!",
  "item.purple.artifact.microscope.name": "Microscopio",
  "item.purple.artifact.microscope.desc": "Uno strumento essenziale per qualsiasi scienziato.",
  "item.purple.artifact.ugly_fish.name": "Pesce Brutto",
  "item.purple.artifact.ugly_fish.desc": "Una.. affascinante, specie di pesce alieno.",
  "item.purple.artifact.potted_plant.name": "Esemplare In Vaso",
  "item.purple.artifact.potted_plant.desc": "Sicuramente non l'albero di bonsai alieno personale di alcuni scienziati.",
  "item.purple.artifact.rope.name": "Corda di Ricambio",
  "item.purple.artifact.rope.desc": "Corda rimasta da una fuga dalle sabbie mobili fallita.",
  "item.purple.artifact.drill.name": "Martello Pneumatico",
  "item.purple.artifact.drill.desc": "Non il più preciso degli strumenti scientifici, ma fa il suo lavoro.",
  "item.purple.artifact.meteorite.name": "Pezzo di Meteorite",
  "item.purple.artifact.meteorite.desc": "L'unico campione di meteorite che abbiamo, un caso estremamente raro.",
  "item.purple.artifact.gears.name": "Ingranaggi Persi",
  "item.purple.artifact.gears.desc": "Come sono arrivati qui? La gru è ancora sicura da usare?",
  "item.purple.artifact.lantern.name": "Lanterna",
  "item.purple.artifact.lantern.desc": "A volte problemi moderni richiedono soluzioni antiche.",
  "item.purple.artifact.test.name": "Supporto per Armatura",
  "item.purple.artifact.test.desc": "Solo un normale supporto per armature per scopi di test.",
  "item.purple.junk.broken_fishing_rod.1": "Rotta in tre punti,",
  "item.purple.junk.broken_fishing_rod.2": "spezzata in uno. Cosa",
  "item.purple.junk.broken_fishing_rod.3": "avrebbe potuto causarlo?",
  "item.purple.junk.sunken_raft": "Zattera Affondata",
  "item.purple.junk.sunken_raft.1": "Sembra che sia stata",
  "item.purple.junk.sunken_raft.2": "trascinata giù, ci sono",
  "item.purple.junk.sunken_raft.3": "anche dei segni di morsi.",
  "item.purple.junk.discarded_fuel_rod": "Barra di Carburante Scartata",
  "item.purple.junk.discarded_fuel_rod.1": "Queste sono solitamente immagazzinate",
  "item.purple.junk.discarded_fuel_rod.2": "responsabilmente. Devono essere",
  "item.purple.junk.discarded_fuel_rod.3": "finite qui per sbaglio.",
  "item.purple.junk.lost_soil_sample": "Campione di Terreno Perduto",
  "item.purple.junk.lost_soil_sample.1": "È vuoto. Beh, pieno",
  "item.purple.junk.lost_soil_sample.2": "d'acqua. Suppongo",
  "item.purple.junk.lost_soil_sample.3": "c'era da aspettarselo.",
  "item.purple.junk.old_brush": "Vecchio Pennello",
  "item.purple.junk.old_brush.1": "Utile per asciugare campioni",
  "item.purple.junk.old_brush.2": "di roccia, quando non",
  "item.purple.junk.old_brush.3": "è bagnato quanto meno.",
  "item.purple.treasure.diving_mask": "Maschera da Sub",
  "item.purple.treasure.diving_mask.1": "Un pezzo di una tuta da sub rotta.",
  "item.purple.treasure.diving_mask.2": "Sembra essere incrinata.",
  "item.purple.treasure.diving_mask.3": "dappertutto.",
  "item.purple.treasure.oxygen_tank": "Bombola di Ossigeno",
  "item.purple.treasure.oxygen_tank.1": "Un pezzo di una tuta da sub rotta.",
  "item.purple.treasure.oxygen_tank.2": "Ancora piena di aria, però",
  "item.purple.treasure.oxygen_tank.3": "è molto graffiata.",
  "item.purple.treasure.wetsuit_pants": "Pantaloni da Sub",
  "item.purple.treasure.wetsuit_pants.1": "Un pezzo di una tuta da sub rotta.",
  "item.purple.treasure.wetsuit_pants.2": "Il tessuto è stato strappato",
  "item.purple.treasure.wetsuit_pants.3": "in diversi punti.",
  "item.purple.treasure.wetsuit_fins": "Pinne",
  "item.purple.treasure.wetsuit_fins.1": "Un pezzo di una tuta da sub rotta.",
  "item.purple.treasure.wetsuit_fins.2": "Sembra come se le pinne",
  "item.purple.treasure.wetsuit_fins.3": "siano state morse.",
  "item.purple.hint_book": "Libro dei Suggerimenti",
  "item.purple.hint_book.locked": "Bloccato",
  "item.purple.hint_book.unlocked": "Disponibile",
  "item.purple.hint_book.how_to_unlock": "Completa un altro Avanzamento\\nSfida per sbloccare questo suggerimento!",
  "item.purple.hint_book.hint": "Suggerimento #%s - %s",
  "item.purple.hint_book.hint.basecamp_brawl.name": "Rissa del Campo Base",
  "item.purple.hint_book.hint.basecamp_brawl.desc": "Sicuramente Il Viola non arriverà\\nmai in questo Campo Base, vero?",
  "item.purple.hint_book.hint.fishe_enjoyer.name": "Apprezzatore di Pesci",
  "item.purple.hint_book.hint.fishe_enjoyer.desc": "a nightlibra piace pescare",
  "item.purple.hint_book.hint.sunken_remains.name": "Resti Affondati",
  "item.purple.hint_book.hint.sunken_remains.desc": "Una tragedia riposa sotto\\nla superficie dell'acqua",
  "item.purple.hint_book.hint.mc_222492.name": "MC-222492",
  "item.purple.hint_book.hint.mc_222492.desc": "Colazione quindi?",
  "item.purple.hint_book.hint.so_hungry.name": "Così Affamato",
  "item.purple.hint_book.hint.so_hungry.desc": "Una deliziosa delizia attende\\nil più stiloso dei vincitori"
}